LICENSE
MANIFEST.in
README.md
setup.cfg
setup.py
bin/parseyml
parseyml/VERSION
parseyml/__init__.py
parseyml/parse_yml.py
parseyml.egg-info/PKG-INFO
parseyml.egg-info/SOURCES.txt
parseyml.egg-info/dependency_links.txt
parseyml.egg-info/requires.txt
parseyml.egg-info/top_level.txt