Metadata-Version: 1.2
Name: parseyml
Version: 0.2.6
Summary: A python executable script to parse yml file and export to shell environment
Home-page: https://github.com/tranvietanh1991/parseyml
Author: V.Anh Tran
Author-email: tranvietanh1991@gmail.com
License: MIT
Download-URL: https://github.com/tranvietanh1991/parseyml/archive/master.zip
Keywords: yaml,parse,parseyml,parse-yml,yml,export,shell
Platform: UNKNOWN
Classifier: Development Status :: 4 - Beta
Classifier: Environment :: Console
Classifier: Intended Audience :: Developers
Classifier: Intended Audience :: System Administrators
Classifier: License :: OSI Approved :: MIT License
Classifier: Operating System :: OS Independent
Classifier: Programming Language :: Python :: 2
Classifier: Programming Language :: Python :: 2.6
Classifier: Programming Language :: Python :: 2.7
Classifier: Topic :: Software Development :: Libraries :: Python Modules
Requires-Python: >=2.6, <3
